mavisim/__init__.py
mavisim/__main__.py
mavisim/astromsim.py
mavisim/generate_image.py
mavisim/py.typed
mavisim/source.py
mavisim/util.py
mavisim/wrapper_for_pyxel.py
mavisim-1.1.20.dist-info/LICENSE
mavisim-1.1.20.dist-info/METADATA
mavisim-1.1.20.dist-info/WHEEL
mavisim-1.1.20.dist-info/entry_points.txt
mavisim-1.1.20.dist-info/top_level.txt
mavisim-1.1.20.dist-info/RECORD
