Metadata-Version: 2.2
Name: mavisim
Version: 1.1.20
Summary: Tool for simulating MAVIS images
Author-email: Stephanie Monty <stephanie.monty@anu.edu.au>, Jesse Cranney <jesse.cranney@anu.edu.au>
License: GNU General Public License (GPL)
Project-URL: Homepage, https://github.com/smonty93/mavisim
Project-URL: Documentation, https://mavisim.readthedocs.io/en/latest/
Classifier: Programming Language :: Python :: 3
Classifier: License :: OSI Approved :: GNU General Public License (GPL)
Classifier: Operating System :: OS Independent
Requires-Python: >=3.9
License-File: LICENSE
Requires-Dist: numpy
Requires-Dist: scipy
Requires-Dist: astropy
Requires-Dist: tqdm>=4.66.4
Requires-Dist: jupyter
Requires-Dist: poppy>=1.1.0
Requires-Dist: pyxel-sim
Provides-Extra: testing
Requires-Dist: pytest; extra == "testing"
Requires-Dist: pytest-cov; extra == "testing"
Requires-Dist: mypy; extra == "testing"
Requires-Dist: flake8; extra == "testing"
Requires-Dist: tox; extra == "testing"
